{
    "profiles" : [
        {
            "header": "I am John Doe",
            "content": "I am an amateur artist, starting strong with quite a few unique art style paintings!",
            "uuid": "001"
        },
        {
            "header": "Hello, World!",
            "content": "This is a description of myself, my content and all",
            "uuid": "001"
        },
        {
            "header": "Hello, World!",
            "content": "This is a description of myself, my content and all",
            "uuid": "001"
        },
        {
            "header": "Hello, World!",
            "content": "This is a description of myself, my content and all",
            "uuid": "001"
        },
        {
            "header": "Hello, World!",
            "content": "This is a description of myself, my content and all",
            "uuid": "001"
        },
        {
            "header": "Hello, World!",
            "content": "This is a description of myself, my content and all",
            "uuid": "001"
        },
        {
            "header": "Hello, World!",
            "content": "This is a description of myself, my content and all",
            "uuid": "001"
        },
        {
            "header": "Hello, World!",
            "content": "This is a description of myself, my content and all",
            "uuid": "001"
        },
        {
            "header": "Hello, World!",
            "content": "This is a description of myself, my content and all",
            "uuid": "001"
        },
        {
            "header": "Hello, World!",
            "content": "This is a description of myself, my content and all",
            "uuid": "001"
        },
        {
            "header": "Hello, World!",
            "content": "This is a description of myself, my content and all",
            "uuid": "001"
        }
        
    ]
}